chatbot/content_generator.py
chatbot/monitoring.py
chatbot/models/facebook_message.py
chatbot/models/response_message.py
chatbot/models/termin.py
chatbot/models/timeframe.py
chatbot/models/user_input_message.py
chatbot/utils/database_utils.py
chatbot/utils/facebook_utils.py
martian_chatbot-0.4.2.dist-info/METADATA
martian_chatbot-0.4.2.dist-info/WHEEL
martian_chatbot-0.4.2.dist-info/top_level.txt
martian_chatbot-0.4.2.dist-info/RECORD
