Metadata-Version: 2.1
Name: martian-chatbot
Version: 0.4.2
Summary: Chatbot creation module
Home-page: https://jzitkovic@gitlab.martianandmachine.com/service/martian-chatbot.git
Author: Josip Zitkovic
Author-email: josip@martian.agency
License: MIT
Platform: UNKNOWN
Requires-Dist: pymongo
Requires-Dist: requests
Requires-Dist: simplejson
